intermine_boot/__init__.py
intermine_boot/archive.py
intermine_boot/commands.py
intermine_boot/intermine.py
intermine_boot/intermine_docker.py
intermine_boot/utils.py
intermine_boot/docker-intermine-gradle/intermine_builder/build.sh
intermine_boot/docker-intermine-gradle/intermine_builder/intermine_builder.Dockerfile
intermine_boot/docker-intermine-gradle/postgres/docker-healthcheck
intermine_boot/docker-intermine-gradle/postgres/init_postgresql.sh
intermine_boot/docker-intermine-gradle/postgres/postgres.Dockerfile
intermine_boot/docker-intermine-gradle/postgres/postgresql.conf
intermine_boot/docker-intermine-gradle/solr/solr.Dockerfile
intermine_boot/docker-intermine-gradle/solr/scripts/intermine.sh
intermine_boot/docker-intermine-gradle/tomcat/tomcat.Dockerfile
intermine_boot/docker-intermine-gradle/tomcat/configs/context.xml
intermine_boot/docker-intermine-gradle/tomcat/configs/server.xml
intermine_boot/docker-intermine-gradle/tomcat/configs/tomcat-users.xml
intermine_boot/docker-intermine-gradle/tomcat/configs/web_context.xml
intermine_boot-0.1.0.dist-info/LICENSE
intermine_boot-0.1.0.dist-info/METADATA
intermine_boot-0.1.0.dist-info/WHEEL
intermine_boot-0.1.0.dist-info/entry_points.txt
intermine_boot-0.1.0.dist-info/top_level.txt
intermine_boot-0.1.0.dist-info/RECORD
