Metadata-Version: 2.1
Name: intermine-boot
Version: 0.1.0
Summary: A CLI tool to spin up local containers in which to build an InterMine.
Home-page: http://www.intermine.org
Author: InterMine team
Author-email: all@intermine.org
License: LGPL
Project-URL: Bug Reports, https://github.com/intermine/intermine_boot/issues
Project-URL: Source, https://github.com/intermine/intermine_boot
Keywords: genomic,bioinformatics
Platform: UNKNOWN
Classifier: Programming Language :: Python :: 3
Classifier: Development Status :: 3 - Alpha
Classifier: Intended Audience :: Science/Research
Classifier: Intended Audience :: Developers
Classifier: License :: OSI Approved :: GNU Library or Lesser General Public License (LGPL)
Classifier: Topic :: Internet :: WWW/HTTP
Classifier: Topic :: Scientific/Engineering :: Bio-Informatics
Classifier: Topic :: Scientific/Engineering :: Information Analysis
Classifier: Operating System :: OS Independent
Requires-Python: >=3.5
License-File: LICENSE
Requires-Dist: Click
Requires-Dist: gitpython
Requires-Dist: xdg
Requires-Dist: pyyaml
Requires-Dist: boto3
Requires-Dist: docker
